fastapi_exception/__init__.py
fastapi_exception/config.py
fastapi_exception/constants/error.py
fastapi_exception/custom_errors/duplicate_error.py
fastapi_exception/custom_errors/missing_error.py
fastapi_exception/custom_errors/string_too_long_error.py
fastapi_exception/custom_errors/string_too_short_error.py
fastapi_exception/custom_errors/validation_error_detail.py
fastapi_exception/exceptions/bad_request.py
fastapi_exception/exceptions/direct_response.py
fastapi_exception/exceptions/entity_not_found.py
fastapi_exception/exceptions/forbidden.py
fastapi_exception/exceptions/gone.py
fastapi_exception/exceptions/not_found.py
fastapi_exception/exceptions/unauthorized.py
fastapi_exception/handlers/global_exception_handler.py
fastapi_exception/handlers/http_exception_handler.py
fastapi_exception/handlers/key_cloak_exception_handler.py
fastapi_exception/handlers/request_exception_handler.py
fastapi_exception/handlers/validation_exception_handler.py
fastapi_exception/translators/base_translator_service.py
fastapi_exception/types/validation_error_detail.py
fastapi_exception/utils/throw_validation.py
fastapi_exception-1.3.10.dist-info/METADATA
fastapi_exception-1.3.10.dist-info/WHEEL
fastapi_exception-1.3.10.dist-info/licenses/LICENSE
fastapi_exception-1.3.10.dist-info/RECORD
