Metadata-Version: 2.3
Name: fastapi_exception
Version: 1.3.10
Summary: FastAPI Exception
Project-URL: Homepage, https://github.com/megatron-global/fastapi-exception
Project-URL: Bug Tracker, https://github.com/megatron-global/fastapi-exception/issues
Author-email: Dzung Nguyen <dung@megatron-solutions.com>
License-File: LICENSE
Classifier: License :: OSI Approved :: MIT License
Classifier: Operating System :: OS Independent
Classifier: Programming Language :: Python :: 3
Requires-Python: >=3.11
Requires-Dist: fastapi-global-variable>=0.0.4
Requires-Dist: pydantic>=2.6.0
Requires-Dist: python-keycloak>=2.14.0
